{"introduction.md":"b02385b5","blogs_01.博客搭建_vitepress引入vue.md":"bc27aa08","blogs_01.博客搭建_utterances评论系统.md":"3f23fe5c","blogs_01.博客搭建_algolia搜索功能.md":"c1c23ea7","blogs_01.博客搭建_看板娘.md":"4313755a","blogs_01.博客搭建_博客架构.md":"2667b50f","blogs_02.openlayers学习_(1)实现聚合标记，点击弹出信息.md":"07363c99","blogs_02.openlayers学习_(2)热力图heatmap.md":"cd7e7cce","blogs_02.openlayers学习_(4)同一图层设置不同的点符号.md":"440a593b","blogs_02.openlayers学习_(8)ol_vue-cli.md":"c1b0a119","blogs_02.openlayers学习_(7)缓冲区的空间相交分析.md":"64939627","blogs_03.css样式_(2)视差.md":"6d623cd9","blogs_04.web基础_post工具.md":"b2744656","blogs_02.openlayers学习_(3)iclient 聚合标签专题图.md":"ddfbedca","blogs_02.openlayers学习_(9)canvas和ol的点标注的避让实现.md":"5877f573","blogs_04.web基础_(2)组件引入.md":"59903f99","blogs_02.openlayers学习_(5)矢量样式编辑器.md":"cdf2503c","blogs_04.web基础_git删除node_module.md":"d7e78c4d","blogs_03.css样式_(1)css_vue页面加载进度条.md":"a69c921b","blogs_04.web基础_(1)webgis基础.md":"795c0878","blogs_04.web基础_js实现文件上传.md":"9ea678f4","blogs_02.openlayers学习_(6)模糊查询 点击定位.md":"01316a06","blogs_03.css样式_(3)css波浪页脚.md":"22d5d46b","blogs_05.ilcs系列_ilcs技术栈.md":"57f0a635","blogs_05.ilcs系列_ilcs之地图组件.md":"d7202d1b","blogs_06.docker_docker容器上传和下载.md":"1cb7c6ca","blogs_05.ilcs系列_ilcs之部署问题.md":"1ceefe4e","blogs_05.ilcs系列_ilcs系统说明文档.md":"f129639a","blogs_06.docker_pca_kmeans.md":"65f1237b","blogs_06.docker_ndvi算法封装.md":"26eff600","blogs_05.ilcs系列_(1)发布一个matlab算法服务.md":"a175b8b4","blogs_06.docker_gdal图像范围匹配.md":"b138dabb","blogs_05.ilcs系列_ilcs之dag图使用.md":"861237da","blogs_06.docker_数据卷操作.md":"e8684411","blogs_06.docker_搭建私有仓库.md":"dfca6c0f","blogs_07.gee_python部署一个gee应用.md":"b7e7335d","blogs_06.docker_自动部署脚本.md":"1a47fdb6","blogs_07.gee_geemap安装.md":"0abe69f0","blogs_06.docker_r语言图像处理.md":"4341a8e9","blogs_08.图像处理_(3)python遍历计算波段.md":"58ac9c2c","blogs_08.图像处理_mat转jpg.md":"124d32c8","blogs_08.图像处理_r语言滤波器.md":"c54a9e5f","blogs_08.图像处理_python裁剪匹配图像区域.md":"9cf369aa","blogs_08.图像处理_变化检测-差值算法.md":"3eb4d121","idea_03.人生观察_人生观察(生活篇).md":"a355d2e4","idea_03.人生观察_教育失衡.md":"e552b684","blogs_index.md":"5e2e9258","idea_程女士_白马村游记-榕树.md":"774b4308","idea_03.人生观察_自我与社会.md":"b5d90928","idea_02.随笔_课题组合照.md":"0f80b28f","knowledge_01.曲谱_(1) 南山南.md":"565ba61f","knowledge_01.coder必修知识_docker镜像及分层详解.md":"3645f505","knowledge_01.coder必修知识_markdown使用语法.md":"e3092713","knowledge_01.曲谱_(2)安河桥.md":"9b2d5989","idea_02.随笔_走马.md":"c23bc456","idea_index.md":"e7a0b650","idea_02.随笔_去爱人.md":"970c6f1c","idea_03.人生观察_人生观察(交往篇).md":"29827e27","idea_02.随笔_浪浪山.md":"77fd3f49","knowledge_01.曲谱_全世界谁倾听你.md":"476b2263","idea_02.随笔_新年随记.md":"1b7ed7ae","index.md":"0a4cea15","knowledge_01.曲谱_(9)玫瑰花的葬礼ukelele.md":"e4a32a98","knowledge_01.曲谱_匆匆那年.md":"0c02cbb5","knowledge_01.曲谱_其实都没有.md":"a3e656f6","knowledge_01.曲谱_吻的太逼真.md":"cd542600","idea_03.人生观察_低欲望社会.md":"6c12d605","knowledge_01.曲谱_(10).庐州月ukelele.md":"87ff0cbd","idea_02.随笔_悲观理想.md":"546efe55","knowledge_01.曲谱_(11).幻听.md":"c0306931","knowledge_01.曲谱_(12).半城烟沙ukelele.md":"6fb97737","idea_02.随笔_情人节独白.md":"fca9e667","blogs_python_折线图.md":"91185d52","blogs_08.图像处理_变化检测精度评价.md":"e7c4931e","knowledge_01.曲谱_(8)清明雨上ukelele.md":"0fe0dfb5","knowledge_01.曲谱_(3)匆匆那年ukulele.md":"b2859583","idea_03.人生观察_关于婚姻.md":"36b2f9ab","idea_02.随笔_玉兰花开.md":"22038e52","knowledge_01.曲谱_(4)大鱼ukulele.md":"05258eda","knowledge_01.coder必修知识_细说浏览器输入url后发生了什么.md":"5458dd7a","knowledge_01.曲谱_莫妮卡.md":"494d4f84","knowledge_01.曲谱_(7)如果当时ukelele.md":"5757af84","idea_02.随笔_柳暗花明.md":"1ae97aa8","idea_02.随笔_死亡教育.md":"769567bb","idea_02.随笔_论文感悟.md":"ecf8a374","knowledge_01.曲谱_(5)忽然之间ukulele.md":"1965e94c","blogs_r语言_r语言http请求.md":"3d72e64d","knowledge_01.coder必修知识_grassgis wiki wps.md":"96174a8f","knowledge_02.cet-6_(2)六级阅读.md":"8f992005","knowledge_01.曲谱_(6)七里香ukelele.md":"af99fcd0","blogs_08.图像处理_变化检测otsu_pca.md":"2fa6b69a","knowledge_01.资源分享_本地挂载阿里云盘.md":"6f834099","knowledge_02.cet-6_(1)六级听力.md":"0350a847","knowledge_01.资源分享_ai与写作工具.md":"102a2506","knowledge_02.cet-6_六级写作.md":"ccda8a84","idea_02.随笔_草籽.md":"dbbd3fa7","knowledge_01.资源分享_mac资源下载站.md":"f7bb260c","idea_02.随笔_欲.md":"3b15ec3c","idea_02.随笔_《宇宙探索编辑部》.md":"fc464d54","knowledge_index.md":"afb4dc05","knowledge_vue_vue的生命周期.md":"5197783c","knowledge_01.资源分享_(2)国内外遥感影像.md":"793464bb","knowledge_02.cet-6_六级翻译.md":"c6063573","knowledge_遥感_基于pca和k-means变化检测.md":"c8bd9520","knowledge_01.资源分享_(1)地球科学数据库（资源检索）.md":"e1b95b28"}
